configkeeper/__init__.py
configkeeper/configkeeper.py
configkeeper-0.1.1.dist-info/AUTHORS.rst
configkeeper-0.1.1.dist-info/LICENSE
configkeeper-0.1.1.dist-info/METADATA
configkeeper-0.1.1.dist-info/WHEEL
configkeeper-0.1.1.dist-info/top_level.txt
configkeeper-0.1.1.dist-info/RECORD
