Metadata-Version: 2.1
Name: configkeeper
Version: 0.1.1
Summary: Backup local config files to repo
Home-page: https://gitlab.com/loxosceles/configkeeper
Author: Magnus "Loxosceles" Henkel
Author-email: loxosceles@gmx.de
License: GNU General Public License v3 (GPLv3)
Keywords: configkeeper
Platform: UNKNOWN
Classifier: Development Status :: 4 - Beta
Classifier: Intended Audience :: System Administrators
Classifier: License :: OSI Approved :: GNU General Public License v3 (GPLv3)
Classifier: Natural Language :: English
Classifier: Operating System :: POSIX :: Linux
Classifier: Programming Language :: Python :: 3
Classifier: Programming Language :: Python :: 3.4
Classifier: Programming Language :: Python :: 3.5
Classifier: Programming Language :: Python :: 3.6
Classifier: Programming Language :: Python :: 3.7
Classifier: Programming Language :: Python :: Implementation :: PyPy
